airflow_providers_impala_to_rdb/ImpalaToRDBSyncOperator.py
airflow_providers_impala_to_rdb/__init__.py
airflow_providers_impala_to_rdb-0.1.6.dist-info/METADATA
airflow_providers_impala_to_rdb-0.1.6.dist-info/WHEEL
airflow_providers_impala_to_rdb-0.1.6.dist-info/top_level.txt
airflow_providers_impala_to_rdb-0.1.6.dist-info/RECORD
