Metadata-Version: 2.1
Name: airflow-providers-impala-to-rdb
Version: 0.1.6
Summary: A custom Airflow operator to upsert data from Impala to PostgreSQL.
Author: Archer Yang
Author-email: archer.yang@crypto.com
Classifier: Programming Language :: Python :: 3
Classifier: Framework :: Apache Airflow
Classifier: License :: OSI Approved :: MIT License
Requires-Dist: impyla
